tablify/__init__.py
tablify/parse.py
tablify/core/__init__.py
tablify/core/html.py
tests/__init__.py
tests/context.py
tests/test_advanced.py
tests/test_basic.py
tablify-0.0.1.dist-info/LICENSE
tablify-0.0.1.dist-info/METADATA
tablify-0.0.1.dist-info/WHEEL
tablify-0.0.1.dist-info/top_level.txt
tablify-0.0.1.dist-info/RECORD
