Metadata-Version: 2.1
Name: tablify
Version: 0.0.1
Summary: This package is used to convert python data structure to html table.
Home-page: https://github.com/ikshitiz/tablify
Author: Kshitij
Author-email: kshtjkmr35@gmail.com
License: UNKNOWN
Platform: UNKNOWN
Classifier: Programming Language :: Python :: 3
Classifier: License :: OSI Approved :: MIT License
Classifier: Operating System :: OS Independent
Requires-Python: >=3.6
